grfcsc/GrfSim.py
grfcsc/GrfStats.py
grfcsc/GrfUtils.py
grfcsc/__init__.py
grfcsc-0.1.0.dist-info/LICENSE
grfcsc-0.1.0.dist-info/METADATA
grfcsc-0.1.0.dist-info/WHEEL
grfcsc-0.1.0.dist-info/top_level.txt
grfcsc-0.1.0.dist-info/RECORD
