Metadata-Version: 2.1
Name: grfcsc
Version: 0.1.0
Summary: A package for Gaussian Random Field simulations and statistics analysis in De Sitter space and Radiation Dominated Universe.
Home-page: https://github.com/khchoi-lmu-physik/grf_qftcs
Author: Ka Hei Choi
Author-email: K.Choi@physik.uni-muenchen.de
Keywords: random field simulation
Classifier: Programming Language :: Python :: 3
Classifier: License :: OSI Approved :: MIT License
Classifier: Operating System :: OS Independent
Requires-Python: >=3.6
License-File: LICENSE
Requires-Dist: numpy
Requires-Dist: matplotlib
Requires-Dist: scipy
